a2w/__init__.py
a2w/a2w.py
a2w/cli.py
a2w-0.1.0.dist-info/METADATA
a2w-0.1.0.dist-info/RECORD
a2w-0.1.0.dist-info/WHEEL
a2w-0.1.0.dist-info/entry_points.txt
a2w-0.1.0.dist-info/top_level.txt
