Metadata-Version: 2.1
Name: a2w
Version: 0.1.0
Summary: TTool  to convert ANSI output to HTML. Optionally it can also upload the result to a web server/service and return a sharable url.
Home-page: https://github.com/ssbarnea/a2w
Author: Sorin Sbarnea
Author-email: sorin.sbarnea@gmail.com
License: MIT license
Keywords: a2w
Platform: UNKNOWN
Classifier: Development Status :: 2 - Pre-Alpha
Classifier: Intended Audience :: Developers
Classifier: License :: OSI Approved :: MIT License
Classifier: Natural Language :: English
Classifier: Programming Language :: Python :: 2
Classifier: Programming Language :: Python :: 2.7
Classifier: Programming Language :: Python :: 3
Classifier: Programming Language :: Python :: 3.4
Classifier: Programming Language :: Python :: 3.5
Classifier: Programming Language :: Python :: 3.6
Classifier: Programming Language :: Python :: 3.7
Requires-Dist: Click (>=6.0)
